[
    {
        "name": "Neato Robotics Botvac D85",
        "url": "https://www.amazon.it/Neato-Robotics-Botvac-D85-aspirapolvere/dp/B00Y2ERFUI/ref=sr_1_1_sspa?ie=UTF8&qid=1539025954&sr=8-1-spons&keywords=neato+botvac+d85&psc=1",
        "currentPrices": {},
        "originalPrices": {}
    },
    {
        "name": "fake 1",
        "url": "https://www.amazon.it/gp/product/B0792MBNHM/ref=s9u_ri_gw_i2?ie=UTF8&pd_rd_i=B0792MBNHM&pd_rd_r=e326326c-cb30-11e8-b31d-abdcac04f0fc&pd_rd_w=4EDbr&pd_rd_wg=XkU84&pf_rd_m=A11IL2PNWYJU7H&pf_rd_s=&pf_rd_r=P6J4H62H258VYQAWVJ1J&pf_rd_t=36701&pf_rd_p=ce4e83db-2fa5-4e86-9bb2-6ea4bd0804f3&pf_rd_i=desktop",
        "currentPrices": {},
        "originalPrices": {}
    },
    {
        "name": "fake 2",
        "url": "https://www.amazon.it/gp/product/8866313092/ref=s9_acsd_newrz_hd_bw_bRvEtb_cr_x__w?pf_rd_m=A11IL2PNWYJU7H&pf_rd_s=merchandised-search-8&pf_rd_r=34CDRV9655530FT58TCB&pf_rd_r=34CDRV9655530FT58TCB&pf_rd_t=101&pf_rd_p=a00b4657-8b6a-59e8-a508-5d36d9fce674&pf_rd_p=a00b4657-8b6a-59e8-a508-5d36d9fce674&pf_rd_i=412603031",
        "currentPrices": {},
        "originalPrices": {}
    },
    {
        "name": "fake 3",
        "url": "https://www.amazon.it/gp/product/B07H1BYQ9B/ref=s9_acsd_newrz_hd_bw_b41uy5n_c_x_w?pf_rd_m=A11IL2PNWYJU7H&pf_rd_s=merchandised-search-5&pf_rd_r=D16YA94TZG5WCK4GET3D&pf_rd_r=D16YA94TZG5WCK4GET3D&pf_rd_t=101&pf_rd_p=135ca927-99b9-506d-b7c1-dcd194d66645&pf_rd_p=135ca927-99b9-506d-b7c1-dcd194d66645&pf_rd_i=3692885031",
        "currentPrices": {},
        "originalPrices": {}
    }
]